winping/__init__.py
winping/__main__.py
winping/errors.py
winping-0.2.4.dist-info/LICENSE
winping-0.2.4.dist-info/METADATA
winping-0.2.4.dist-info/WHEEL
winping-0.2.4.dist-info/entry_points.txt
winping-0.2.4.dist-info/top_level.txt
winping-0.2.4.dist-info/zip-safe
winping-0.2.4.dist-info/RECORD
